{
  "version": "7",
  "dialect": "postgresql",
  "entries": [
    {
      "idx": 0,
      "version": "7",
      "when": 1772797406694,
      "tag": "0000_ambitious_owl",
      "breakpoints": true
    },
    {
      "idx": 1,
      "version": "7",
      "when": 1772799205720,
      "tag": "0001_slim_newton_destine",
      "breakpoints": true
    },
    {
      "idx": 2,
      "version": "7",
      "when": 1772827888573,
      "tag": "0002_late_zzzax",
      "breakpoints": true
    },
    {
      "idx": 3,
      "version": "7",
      "when": 1772832820292,
      "tag": "0003_fine_silver_centurion",
      "breakpoints": true
    },
    {
      "idx": 4,
      "version": "7",
      "when": 1772970349595,
      "tag": "0004_bitter_flatman",
      "breakpoints": true
    },
    {
      "idx": 5,
      "version": "7",
      "when": 1772971377772,
      "tag": "0005_aberrant_spiral",
      "breakpoints": true
    },
    {
      "idx": 6,
      "version": "7",
      "when": 1773058455601,
      "tag": "0006_talented_tomorrow_man",
      "breakpoints": true
    },
    {
      "idx": 7,
      "version": "7",
      "when": 1773214951515,
      "tag": "0007_third_gauntlet",
      "breakpoints": true
    },
    {
      "idx": 8,
      "version": "7",
      "when": 1773281362227,
      "tag": "0008_fresh_lyja",
      "breakpoints": true
    },
    {
      "idx": 9,
      "version": "7",
      "when": 1773284809946,
      "tag": "0009_flowery_marrow",
      "breakpoints": true
    }
  ]
}